src/hydro/__init__.py
src/hydro/hydro.py
hydro_relic374-0.0.2.dist-info/METADATA
hydro_relic374-0.0.2.dist-info/WHEEL
hydro_relic374-0.0.2.dist-info/licenses/LICENSE
hydro_relic374-0.0.2.dist-info/RECORD
