Metadata-Version: 2.1
Name: hydro_relic374
Version: 0.0.2
Summary: An easy & simple way to package electron apps
Project-URL: Homepage, https://github.com/relic374/hydro
Project-URL: Bug Tracker, https://github.com/relic374/hydro/issues
Author-email: Relic374 <magmis358@gmail.com>
License: Hydro Electron Packager
Classifier: License :: OSI Approved :: MIT License
Classifier: Operating System :: OS Independent
Classifier: Programming Language :: Python :: 3
Requires-Python: >=3.7
Requires-Dist: termcolor
